opentotp/__init__.py
opentotp/__main__.py
opentotp/opentotp.py
opentotp-1.0.0.dist-info/LICENSE
opentotp-1.0.0.dist-info/METADATA
opentotp-1.0.0.dist-info/WHEEL
opentotp-1.0.0.dist-info/entry_points.txt
opentotp-1.0.0.dist-info/top_level.txt
opentotp-1.0.0.dist-info/RECORD
