Metadata-Version: 2.1
Name: opentotp
Version: 1.0.0
Summary: Yet another Time-based, One-Time-Passwords Generator/Verifier
Home-page: https://github.com/prevenitylabs/opentotp
Author: Prevenity Labs
Author-email: info@prevenity.com
License: MIT
Platform: UNKNOWN
Classifier: Development Status :: 4 - Beta
Classifier: Environment :: Console
Classifier: Intended Audience :: Developers
Classifier: License :: OSI Approved :: MIT License
Classifier: Programming Language :: Python :: 3
Classifier: Programming Language :: Python :: 3.8
Requires-Dist: base58 (>=2.1.1)
